maad/__init__.py
maad/version.py
maad/features/__init__.py
maad/features/alpha_indices.py
maad/features/composite_soundscape_descriptors.py
maad/features/shape.py
maad/features/spectral.py
maad/features/temporal.py
maad/rois/__init__.py
maad/rois/rois_1d.py
maad/rois/rois_2d.py
maad/rois/template_matching_func.py
maad/sound/__init__.py
maad/sound/filter.py
maad/sound/input_output.py
maad/sound/metrics.py
maad/sound/spectral_subtraction.py
maad/sound/spectro_func.py
maad/sound/transform.py
maad/sound/trim_func.py
maad/spl/__init__.py
maad/spl/active_space.py
maad/spl/conversion_SPL.py
maad/util/__init__.py
maad/util/audio_metadata_utilities.py
maad/util/math_func.py
maad/util/miscellaneous.py
maad/util/parser.py
maad/util/visualization.py
maad/util/xeno_canto.py
scikit_maad-1.5.1.dist-info/LICENSE
scikit_maad-1.5.1.dist-info/WHEEL
scikit_maad-1.5.1.dist-info/METADATA
scikit_maad-1.5.1.dist-info/RECORD
