Metadata-Version: 2.1
Name: scikit-maad
Version: 1.5.1
Summary: Open-source and modular toolbox for quantitative soundscape analysis in Python
Keywords: ecoacoustics,bioacoustics,ecology,sound pressure level,signal processing
Author-email: scikit-maad developers <scikit.maad@gmail.com>
Requires-Python: >=3.9
Classifier: Development Status :: 4 - Beta
Classifier: Intended Audience :: Science/Research
Classifier: Intended Audience :: Developers
Classifier: License :: OSI Approved :: BSD License
Classifier: Operating System :: Microsoft :: Windows
Classifier: Operating System :: Unix
Classifier: Operating System :: MacOS
Classifier: Programming Language :: Python :: 3.9
Classifier: Programming Language :: Python :: 3.10
Classifier: Programming Language :: Python :: 3.11
Classifier: Programming Language :: Python :: 3.12
Classifier: Topic :: Software Development :: Libraries
Classifier: Topic :: Scientific/Engineering :: Artificial Intelligence
Requires-Dist: numpy >=1.21
Requires-Dist: scipy >=1.8
Requires-Dist: scikit-image >=0.23.1
Requires-Dist: pandas >=1.5
Requires-Dist: matplotlib >=3.6
Requires-Dist: pywavelets >=1.4
Requires-Dist: flit >=3.6 ; extra == "build"
Requires-Dist: sphinx >=5.0 ; extra == "doc"
Requires-Dist: pytest >=7.1 ; extra == "test"
Requires-Dist: pytest-cov >=4.0 ; extra == "test"
Project-URL: Documentation, https://scikit-maad.github.io/
Project-URL: Home, https://github.com/scikit-maad/scikit-maad
Project-URL: Source, https://github.com/scikit-maad/scikit-maad
Project-URL: Tracker, https://github.com/scikit-maad/scikit-maad/issues
Provides-Extra: build
Provides-Extra: doc
Provides-Extra: test
